{
  "username": "stacks",
  "generated_at": "2026-07-22T19:29:07.181817+00:00",
  "cells": [
    {
      "index": 0,
      "row": 0,
      "col": 0,
      "category": "Hard",
      "text": "A mansard-roof Pizza Hut building (can be still operating as a Pizza Hut, have another business in it, or vacant; representative examples)",
      "urls": [
        "https://usedtobeapizzahut.com/"
      ],
      "inline_links": [
        {
          "text": "representative examples",
          "url": "https://usedtobeapizzahut.com/"
        }
      ]
    },
    {
      "index": 1,
      "row": 0,
      "col": 1,
      "category": "Easy",
      "text": "Sporting event center for any professional or college sport/team",
      "urls": [],
      "inline_links": []
    },
    {
      "index": 2,
      "row": 0,
      "col": 2,
      "category": "Medium",
      "text": "Any farm equipment",
      "urls": [],
      "inline_links": []
    },
    {
      "index": 3,
      "row": 0,
      "col": 3,
      "category": "Hard",
      "text": "A civil defense/weather siren",
      "urls": [],
      "inline_links": []
    },
    {
      "index": 4,
      "row": 0,
      "col": 4,
      "category": "Easy license plate letter/number game, only one per card from this category",
      "text": "A license plate serial containing the letter Q",
      "urls": [],
      "inline_links": []
    },
    {
      "index": 5,
      "row": 1,
      "col": 0,
      "category": "Easy",
      "text": "A sign for any highway concurrency (interstate/US highway/state highway/county road sharing the same roadway)",
      "urls": [],
      "inline_links": []
    },
    {
      "index": 6,
      "row": 1,
      "col": 1,
      "category": "Easy",
      "text": "Advertisement for Coca-Cola",
      "urls": [],
      "inline_links": []
    },
    {
      "index": 7,
      "row": 1,
      "col": 2,
      "category": "Medium",
      "text": "A well (decorative or functional)",
      "urls": [],
      "inline_links": []
    },
    {
      "index": 8,
      "row": 1,
      "col": 3,
      "category": "Hard",
      "text": "A drive-in restaurant or movie theater that calls itself a drive-in on its signage/Google Maps POI",
      "urls": [],
      "inline_links": []
    },
    {
      "index": 9,
      "row": 1,
      "col": 4,
      "category": "Easy",
      "text": "A sign displaying the local current time",
      "urls": [],
      "inline_links": []
    },
    {
      "index": 10,
      "row": 2,
      "col": 0,
      "category": "Easy",
      "text": "A yellow automobile (taxis and school buses count)",
      "urls": [],
      "inline_links": []
    },
    {
      "index": 11,
      "row": 2,
      "col": 1,
      "category": "Easy",
      "text": "Advertisement for any beer",
      "urls": [],
      "inline_links": []
    },
    {
      "index": 12,
      "row": 2,
      "col": 2,
      "category": "Free",
      "text": "any photo of your choice",
      "urls": [],
      "inline_links": []
    },
    {
      "index": 13,
      "row": 2,
      "col": 3,
      "category": "Medium",
      "text": "Pay phone, phone booth, or sign for either (if it's a sign, the phone doesn't have to still be there)",
      "urls": [],
      "inline_links": []
    },
    {
      "index": 14,
      "row": 2,
      "col": 4,
      "category": "Easy",
      "text": "Any historical marker or plaque",
      "urls": [],
      "inline_links": []
    },
    {
      "index": 15,
      "row": 3,
      "col": 0,
      "category": "Hard",
      "text": "Sign indicating a distance more than 250 miles",
      "urls": [],
      "inline_links": []
    },
    {
      "index": 16,
      "row": 3,
      "col": 1,
      "category": "Medium",
      "text": "A Bible verse reference or full text",
      "urls": [],
      "inline_links": []
    },
    {
      "index": 17,
      "row": 3,
      "col": 2,
      "category": "Easy",
      "text": "A neon sign (anything clearly in the neon style counts even if it's not true neon)",
      "urls": [],
      "inline_links": []
    },
    {
      "index": 18,
      "row": 3,
      "col": 3,
      "category": "Easy",
      "text": "Private property/no trespassing sign",
      "urls": [],
      "inline_links": []
    },
    {
      "index": 19,
      "row": 3,
      "col": 4,
      "category": "Easy",
      "text": "A sign for a road named after any kind of tree",
      "urls": [],
      "inline_links": []
    },
    {
      "index": 20,
      "row": 4,
      "col": 0,
      "category": "Medium",
      "text": "A picture of the thing a street is named for, visible from or located on that street (e.g. a sunset taken from Sunset Boulevard; an oak tree on Oak Street)",
      "urls": [],
      "inline_links": []
    },
    {
      "index": 21,
      "row": 4,
      "col": 1,
      "category": "Medium",
      "text": "A non-US national flag",
      "urls": [],
      "inline_links": []
    },
    {
      "index": 22,
      "row": 4,
      "col": 2,
      "category": "Easy",
      "text": "Any wildlife/animal warning sign",
      "urls": [],
      "inline_links": []
    },
    {
      "index": 23,
      "row": 4,
      "col": 3,
      "category": "Hard",
      "text": "Advertisement for a local radio station",
      "urls": [],
      "inline_links": []
    },
    {
      "index": 24,
      "row": 4,
      "col": 4,
      "category": "Medium",
      "text": "Any US state flag",
      "urls": [],
      "inline_links": []
    }
  ]
}